fastcontext/__init__.py
fastcontext/fastcontext.py
fastcontext-2022.8.30.dist-info/METADATA
fastcontext-2022.8.30.dist-info/WHEEL
fastcontext-2022.8.30.dist-info/entry_points.txt
fastcontext-2022.8.30.dist-info/licenses/LICENSE
fastcontext-2022.8.30.dist-info/RECORD
