Metadata-Version: 2.1
Name: FastContext
Version: 2022.8.30
Summary: A tool for identification of adapters and other sequence patterns in the next generation sequencing (NGS) data
Project-URL: Homepage, https://github.com/regnveig/FastContext
Project-URL: Bug Tracker, https://github.com/regnveig/FastContext/issues
Author-email: Emil Viesná <regnveig@yandex.ru>
Keywords: NGS,adapters,bioinformatics,read,structure
Classifier: Development Status :: 4 - Beta
Classifier: Environment :: Console
Classifier: Intended Audience :: Science/Research
Classifier: License :: OSI Approved :: GNU General Public License v3 (GPLv3)
Classifier: Natural Language :: English
Classifier: Operating System :: OS Independent
Classifier: Programming Language :: Python :: 3.8
Classifier: Programming Language :: Python :: 3.9
Classifier: Programming Language :: Python :: 3.10
Classifier: Topic :: Scientific/Engineering :: Bio-Informatics
Requires-Python: >=3.8
Requires-Dist: biopython>=1.79
Requires-Dist: pandas>=1.2.5
Requires-Dist: python-levenshtein>=0.12.2
Requires-Dist: tqdm>=4.61.2
